{
  "type": 3,
  "data": {
    "source": 1,
    "positions": [
      {
        "x": 900,
        "y": 444,
        "id": 776,
        "timeOffset": -450
      },
      {
        "x": 953,
        "y": 433,
        "id": 776,
        "timeOffset": -400
      },
      {
        "x": 986,
        "y": 413,
        "id": 776,
        "timeOffset": -350
      },
      {
        "x": 1016,
        "y": 389,
        "id": 776,
        "timeOffset": -300
      },
      {
        "x": 1048,
        "y": 368,
        "id": 776,
        "timeOffset": -250
      },
      {
        "x": 1076,
        "y": 350,
        "id": 776,
        "timeOffset": -200
      },
      {
        "x": 1112,
        "y": 324,
        "id": 776,
        "timeOffset": -150
      },
      {
        "x": 1149,
        "y": 298,
        "id": 732,
        "timeOffset": -100
      },
      {
        "x": 1192,
        "y": 264,
        "id": 732,
        "timeOffset": -50
      },
      {
        "x": 1267,
        "y": 233,
        "id": 732,
        "timeOffset": 0
      }
    ]
  },
  "timestamp": 1724407136919
}