{
  "type": 3,
  "data": {
    "source": 0,
    "texts": [],
    "attributes": [
      {
        "id": 769,
        "attributes": {
          "style": {
            "transform": "translate(-78.7554%, 0%) translate3d(0px, 0px, 0px)"
          }
        }
      },
      {
        "id": 766,
        "attributes": {
          "style": {
            "transform": "translate(-78.7554%, 0%) translate3d(0px, 0px, 0px)"
          }
        }
      },
      {
        "id": 763,
        "attributes": {
          "style": {
            "transform": "translate(-78.7554%, 0%) translate3d(0px, 0px, 0px)"
          }
        }
      },
      {
        "id": 760,
        "attributes": {
          "style": {
            "transform": "translate(-78.7554%, 0%) translate3d(0px, 0px, 0px)"
          }
        }
      },
      {
        "id": 756,
        "attributes": {
          "style": {
            "transform": "translate(-78.7554%, 0%) translate3d(0px, 0px, 0px)"
          }
        }
      },
      {
        "id": 751,
        "attributes": {
          "style": {
            "transform": "translate(-78.7554%, 0%) translate3d(0px, 0px, 0px)"
          }
        }
      },
      {
        "id": 748,
        "attributes": {
          "style": {
            "transform": "translate(-78.7554%, 0%) translate3d(0px, 0px, 0px)"
          }
        }
      },
      {
        "id": 745,
        "attributes": {
          "style": {
            "transform": "translate(-78.7554%, 0%) translate3d(0px, 0px, 0px)"
          }
        }
      },
      {
        "id": 742,
        "attributes": {
          "style": {
            "transform": "translate(-78.7554%, 0%) translate3d(0px, 0px, 0px)"
          }
        }
      },
      {
        "id": 738,
        "attributes": {
          "style": {
            "transform": "translate(-78.7554%, 0%) translate3d(0px, 0px, 0px)"
          }
        }
      },
      {
        "id": 772,
        "attributes": {
          "style": {
            "transform": "translate(0%, -47.2007%) translate3d(0px, 0px, 0px)",
            "opacity": "0.2114"
          }
        }
      },
      {
        "id": 908,
        "attributes": {
          "style": {
            "opacity": "0.7304"
          }
        }
      },
      {
        "id": 864,
        "attributes": {
          "style": {
            "opacity": "0.7304"
          }
        }
      },
      {
        "id": 820,
        "attributes": {
          "style": {
            "opacity": "0.7304"
          }
        }
      },
      {
        "id": 776,
        "attributes": {
          "style": {
            "opacity": "0.7304"
          }
        }
      },
      {
        "id": 732,
        "attributes": {
          "style": {
            "opacity": "0.7304"
          }
        }
      },
      {
        "id": 697,
        "attributes": {
          "style": {
            "opacity": "0.7304"
          }
        }
      },
      {
        "id": 656,
        "attributes": {
          "style": {
            "opacity": "0.7304"
          }
        }
      },
      {
        "id": 355,
        "attributes": {
          "style": {
            "transform": "translate(73.0353%, 0%) translate3d(0px, 0px, 0px)"
          }
        }
      },
      {
        "id": 348,
        "attributes": {
          "style": {
            "transform": "translate(0%, 73.0353%) translate3d(0px, 0px, 0px)",
            "opacity": "0.2696"
          }
        }
      },
      {
        "id": 389,
        "attributes": {
          "style": {
            "transform": "translate(0%, 73.0353%) translate3d(0px, 0px, 0px)",
            "opacity": "0.2696"
          }
        }
      },
      {
        "id": 394,
        "attributes": {
          "style": {
            "opacity": "0.2696",
            "transform": "translate(-21.9106%, 0%) translate3d(0px, 0px, 0px) scale(0.927, 0.927)"
          }
        }
      },
      {
        "id": 401,
        "attributes": {
          "style": {
            "opacity": "0.2696",
            "transform": "translate(21.9106%, 0%) translate3d(0px, 0px, 0px) scale(0.927, 0.927)"
          }
        }
      },
      {
        "id": 132,
        "attributes": {
          "style": {
            "transform": "translate3d(-102.564px, 43.8691px, 0px) scale(1.0326, 1.0327)",
            "opacity": "0.9911"
          }
        }
      },
      {
        "id": 127,
        "attributes": {
          "style": {
            "transform": "translate3d(334.638px, -39.9496px, 0px) scale(1.0468, 1.0469)",
            "opacity": "0.9936"
          }
        }
      },
      {
        "id": 122,
        "attributes": {
          "style": {
            "transform": "translate3d(267.501px, -106.173px, 0px) scale(1.0639, 1.064)",
            "opacity": "0.9955"
          }
        }
      },
      {
        "id": 117,
        "attributes": {
          "style": {
            "transform": "translate3d(-112.973px, 1.7662px, 0px) scale(1.0814, 1.0815)",
            "opacity": "0.997"
          }
        }
      },
      {
        "id": 359,
        "attributes": {
          "style": {
            "transform": "translate(92.0188%, 0%) translate3d(0px, 0px, 0px)"
          }
        }
      }
    ],
    "removes": [],
    "adds": []
  },
  "timestamp": 1724407138939
}