{
  "type": 3,
  "data": {
    "source": 0,
    "texts": [],
    "attributes": [
      {
        "id": 734,
        "attributes": {
          "style": {
            "transform": "translate3d(32.5264px, 0px, 0px)"
          }
        }
      },
      {
        "id": 772,
        "attributes": {
          "style": {
            "transform": "translate(0%, 13.4423%) translate3d(0px, 0px, 0px)",
            "opacity": "0.3495"
          }
        }
      },
      {
        "id": 132,
        "attributes": {
          "style": {
            "transform": "translate3d(0px, 0px, 0px) scale(0.6352, 0.6352)",
            "opacity": "0.2704"
          }
        }
      },
      {
        "id": 127,
        "attributes": {
          "style": {
            "transform": "translate3d(0px, 0px, 0px) scale(0.6569, 0.6569)",
            "opacity": "0.3138"
          }
        }
      },
      {
        "id": 122,
        "attributes": {
          "style": {
            "transform": "translate3d(0px, 0px, 0px) scale(0.6685, 0.6685)",
            "opacity": "0.337"
          }
        }
      },
      {
        "id": 117,
        "attributes": {
          "style": {
            "transform": "translate3d(0px, 0px, 0px) scale(0.6747, 0.6747)",
            "opacity": "0.3495"
          }
        }
      },
      {
        "id": 778,
        "attributes": {
          "style": {
            "transform": "translate3d(19.751px, 0px, 0px)"
          }
        }
      },
      {
        "id": 816,
        "attributes": {
          "style": {
            "transform": "translate(0%, 19.751%) translate3d(0px, 0px, 0px)",
            "opacity": "0.605"
          }
        }
      },
      {
        "id": 140,
        "attributes": {
          "style": {
            "transform": "translate3d(0px, 0px, 0px) scale(0.8025, 0.8025)",
            "opacity": "0.605"
          }
        }
      },
      {
        "id": 145,
        "attributes": {
          "style": {
            "transform": "translate3d(0px, 0px, 0px) scale(0.6314, 0.6314)",
            "opacity": "0.2629"
          }
        }
      }
    ],
    "removes": [],
    "adds": []
  },
  "timestamp": 1724407130302
}