{
  "type": 3,
  "data": {
    "source": 0,
    "texts": [],
    "attributes": [
      {
        "id": 769,
        "attributes": {
          "style": {
            "transform": "translate(-35.4123%, 0%) translate3d(0px, 0px, 0px)"
          }
        }
      },
      {
        "id": 766,
        "attributes": {
          "style": {
            "transform": "translate(-35.4123%, 0%) translate3d(0px, 0px, 0px)"
          }
        }
      },
      {
        "id": 763,
        "attributes": {
          "style": {
            "transform": "translate(-35.4123%, 0%) translate3d(0px, 0px, 0px)"
          }
        }
      },
      {
        "id": 760,
        "attributes": {
          "style": {
            "transform": "translate(-35.4123%, 0%) translate3d(0px, 0px, 0px)"
          }
        }
      },
      {
        "id": 756,
        "attributes": {
          "style": {
            "transform": "translate(-35.4123%, 0%) translate3d(0px, 0px, 0px)"
          }
        }
      },
      {
        "id": 751,
        "attributes": {
          "style": {
            "transform": "translate(-35.4123%, 0%) translate3d(0px, 0px, 0px)"
          }
        }
      },
      {
        "id": 748,
        "attributes": {
          "style": {
            "transform": "translate(-35.4123%, 0%) translate3d(0px, 0px, 0px)"
          }
        }
      },
      {
        "id": 745,
        "attributes": {
          "style": {
            "transform": "translate(-35.4123%, 0%) translate3d(0px, 0px, 0px)"
          }
        }
      },
      {
        "id": 742,
        "attributes": {
          "style": {
            "transform": "translate(-35.4123%, 0%) translate3d(0px, 0px, 0px)"
          }
        }
      },
      {
        "id": 738,
        "attributes": {
          "style": {
            "transform": "translate(-35.4123%, 0%) translate3d(0px, 0px, 0px)"
          }
        }
      },
      {
        "id": 772,
        "attributes": {
          "style": {
            "transform": "translate(0%, -21.2474%) translate3d(0px, 0px, 0px)",
            "opacity": "0.6459"
          }
        }
      },
      {
        "id": 132,
        "attributes": {
          "style": {
            "transform": "translate3d(-274.95px, 117.603px, 0px) scale(1.101, 1.1011)"
          }
        }
      },
      {
        "id": 127,
        "attributes": {
          "style": {
            "transform": "translate3d(733.513px, -87.568px, 0px) scale(1.1106, 1.1107)"
          }
        }
      },
      {
        "id": 122,
        "attributes": {
          "style": {
            "transform": "translate3d(474.809px, -188.454px, 0px) scale(1.118, 1.1181)"
          }
        }
      },
      {
        "id": 117,
        "attributes": {
          "style": {
            "transform": "translate3d(-167.883px, 2.6246px, 0px) scale(1.1236, 1.1237)"
          }
        }
      }
    ],
    "removes": [],
    "adds": []
  },
  "timestamp": 1724407581573
}