{
  "type": 3,
  "data": {
    "source": 0,
    "texts": [],
    "attributes": [
      {
        "id": 394,
        "attributes": {
          "style": {
            "opacity": "0.0037",
            "transform": "translate(-79.705%, 0%) translate3d(0px, 0px, 0px) scale(0.9004, 0.9004)"
          }
        }
      },
      {
        "id": 401,
        "attributes": {
          "style": {
            "opacity": "0.0037",
            "transform": "translate(79.705%, 0%) translate3d(0px, 0px, 0px) scale(0.9004, 0.9004)"
          }
        }
      },
      {
        "id": 348,
        "attributes": {
          "style": {
            "transform": "translate(0%, -99.6313%) translate3d(0px, 0px, 0px)",
            "opacity": "0.0037"
          }
        }
      },
      {
        "id": 389,
        "attributes": {
          "style": {
            "transform": "translate(0%, -99.6313%) translate3d(0px, 0px, 0px)",
            "opacity": "0.0037"
          }
        }
      },
      {
        "id": 386,
        "attributes": {
          "style": {
            "transform": "translate(99.6313%, 0%) translate3d(0px, 0px, 0px)"
          }
        }
      },
      {
        "id": 383,
        "attributes": {
          "style": {
            "transform": "translate(99.6313%, 0%) translate3d(0px, 0px, 0px)"
          }
        }
      },
      {
        "id": 380,
        "attributes": {
          "style": {
            "transform": "translate(99.6313%, 0%) translate3d(0px, 0px, 0px)"
          }
        }
      },
      {
        "id": 377,
        "attributes": {
          "style": {
            "transform": "translate(99.6313%, 0%) translate3d(0px, 0px, 0px)"
          }
        }
      },
      {
        "id": 373,
        "attributes": {
          "style": {
            "transform": "translate(99.6313%, 0%) translate3d(0px, 0px, 0px)"
          }
        }
      },
      {
        "id": 368,
        "attributes": {
          "style": {
            "transform": "translate(99.6313%, 0%) translate3d(0px, 0px, 0px)"
          }
        }
      },
      {
        "id": 365,
        "attributes": {
          "style": {
            "transform": "translate(99.6313%, 0%) translate3d(0px, 0px, 0px)"
          }
        }
      },
      {
        "id": 362,
        "attributes": {
          "style": {
            "transform": "translate(99.6313%, 0%) translate3d(0px, 0px, 0px)"
          }
        }
      },
      {
        "id": 359,
        "attributes": {
          "style": {
            "transform": "translate(99.6313%, 0%) translate3d(0px, 0px, 0px)"
          }
        }
      },
      {
        "id": 355,
        "attributes": {
          "style": {
            "transform": "translate(99.6313%, 0%) translate3d(0px, 0px, 0px)"
          }
        }
      },
      {
        "id": 908,
        "attributes": {
          "style": {
            "opacity": "0.9628"
          }
        }
      },
      {
        "id": 864,
        "attributes": {
          "style": {
            "opacity": "0.9628"
          }
        }
      },
      {
        "id": 820,
        "attributes": {
          "style": {
            "opacity": "0.9628"
          }
        }
      },
      {
        "id": 776,
        "attributes": {
          "style": {
            "opacity": "0.9628"
          }
        }
      },
      {
        "id": 732,
        "attributes": {
          "style": {
            "opacity": "0.9628"
          }
        }
      },
      {
        "id": 697,
        "attributes": {
          "style": {
            "opacity": "0.9628"
          }
        }
      },
      {
        "id": 656,
        "attributes": {
          "style": {
            "opacity": "0.9628"
          }
        }
      },
      {
        "id": 772,
        "attributes": {
          "style": {
            "transform": "translate(0%, -2.2298%) translate3d(0px, 0px, 0px)"
          }
        }
      },
      {
        "id": 769,
        "attributes": {
          "style": {
            "transform": "translate(-3.7163%, 0%) translate3d(0px, 0px, 0px)"
          }
        }
      },
      {
        "id": 766,
        "attributes": {
          "style": {
            "transform": "translate(-4.6822%, 0%) translate3d(0px, 0px, 0px)"
          }
        }
      },
      {
        "id": 763,
        "attributes": {
          "style": {
            "transform": "translate(-5.8992%, 0%) translate3d(0px, 0px, 0px)"
          }
        }
      },
      {
        "id": 760,
        "attributes": {
          "style": {
            "transform": "translate(-7.4325%, 0%) translate3d(0px, 0px, 0px)"
          }
        }
      },
      {
        "id": 756,
        "attributes": {
          "style": {
            "transform": "translate(-9.3644%, 0%) translate3d(0px, 0px, 0px)"
          }
        }
      },
      {
        "id": 751,
        "attributes": {
          "style": {
            "transform": "translate(-11.7984%, 0%) translate3d(0px, 0px, 0px)"
          }
        }
      },
      {
        "id": 748,
        "attributes": {
          "style": {
            "transform": "translate(-14.8651%, 0%) translate3d(0px, 0px, 0px)"
          }
        }
      },
      {
        "id": 745,
        "attributes": {
          "style": {
            "transform": "translate(-18.7288%, 0%) translate3d(0px, 0px, 0px)"
          }
        }
      },
      {
        "id": 742,
        "attributes": {
          "style": {
            "transform": "translate(-23.5969%, 0%) translate3d(0px, 0px, 0px)"
          }
        }
      },
      {
        "id": 738,
        "attributes": {
          "style": {
            "transform": "translate(-29.7302%, 0%) translate3d(0px, 0px, 0px)"
          }
        }
      },
      {
        "id": 132,
        "attributes": {
          "style": {
            "transform": "translate3d(1.6674px, -0.7126px, 0px) scale(0.9995, 0.9995)",
            "opacity": "0.0045"
          }
        }
      },
      {
        "id": 127,
        "attributes": {
          "style": {
            "transform": "translate3d(-4.0626px, 0.4855px, 0px) scale(0.9995, 0.9995)",
            "opacity": "0.0045"
          }
        }
      },
      {
        "id": 122,
        "attributes": {
          "style": {
            "transform": "translate3d(-2.4652px, 0.9791px, 0px) scale(0.9995, 0.9995)",
            "opacity": "0.0045"
          }
        }
      },
      {
        "id": 117,
        "attributes": {
          "style": {
            "transform": "translate3d(0.8328px, -0.0126px, 0px) scale(0.9995, 0.9995)",
            "opacity": "0.0045"
          }
        }
      }
    ],
    "removes": [],
    "adds": []
  },
  "timestamp": 1724407583424
}