{
  "type": 3,
  "data": {
    "source": 0,
    "texts": [],
    "attributes": [
      {
        "id": 690,
        "attributes": {
          "style": {
            "transform": "translate(-16.6589%, 0%) translate3d(0px, 0px, 0px)"
          }
        }
      },
      {
        "id": 687,
        "attributes": {
          "style": {
            "transform": "translate(-16.6589%, 0%) translate3d(0px, 0px, 0px)"
          }
        }
      },
      {
        "id": 684,
        "attributes": {
          "style": {
            "transform": "translate(-16.6589%, 0%) translate3d(0px, 0px, 0px)"
          }
        }
      },
      {
        "id": 681,
        "attributes": {
          "style": {
            "transform": "translate(-16.6589%, 0%) translate3d(0px, 0px, 0px)"
          }
        }
      },
      {
        "id": 677,
        "attributes": {
          "style": {
            "transform": "translate(-16.6589%, 0%) translate3d(0px, 0px, 0px)"
          }
        }
      },
      {
        "id": 672,
        "attributes": {
          "style": {
            "transform": "translate(-16.6589%, 0%) translate3d(0px, 0px, 0px)"
          }
        }
      },
      {
        "id": 669,
        "attributes": {
          "style": {
            "transform": "translate(-16.6589%, 0%) translate3d(0px, 0px, 0px)"
          }
        }
      },
      {
        "id": 666,
        "attributes": {
          "style": {
            "transform": "translate(-16.6589%, 0%) translate3d(0px, 0px, 0px)"
          }
        }
      },
      {
        "id": 662,
        "attributes": {
          "style": {
            "transform": "translate(-16.6589%, 0%) translate3d(0px, 0px, 0px)"
          }
        }
      },
      {
        "id": 693,
        "attributes": {
          "style": {
            "transform": "translate(0%, -9.9953%) translate3d(0px, 0px, 0px)",
            "opacity": "0.8334"
          }
        }
      },
      {
        "id": 86,
        "attributes": {
          "style": {
            "transform": "translate3d(-494.576px, 99.7992px, 0px) scale(1.1207, 1.1208)"
          }
        }
      },
      {
        "id": 81,
        "attributes": {
          "style": {
            "transform": "translate3d(832.962px, -23.0893px, 0px) scale(1.1256, 1.1257)"
          }
        }
      },
      {
        "id": 76,
        "attributes": {
          "style": {
            "transform": "translate3d(197.306px, -49.3029px, 0px) scale(1.1292, 1.1293)"
          }
        }
      },
      {
        "id": 71,
        "attributes": {
          "style": {
            "transform": "translate3d(-344.112px, -227.896px, 0px) scale(1.1318, 1.1319)"
          }
        }
      }
    ],
    "removes": [],
    "adds": []
  },
  "timestamp": 1724407585223
}